multi_search/__init__.py
multi_search/baidu_search.py
multi_search/bing_search.py
multi_search/duckduckgo_search.py
multi_search/google_search.py
multi_search/main.py
multi_search/test.py
multi_search/yahoo_search.py
multi_search_engine-1.0.1.dist-info/LICENSE
multi_search_engine-1.0.1.dist-info/METADATA
multi_search_engine-1.0.1.dist-info/WHEEL
multi_search_engine-1.0.1.dist-info/top_level.txt
multi_search_engine-1.0.1.dist-info/RECORD
